sch/__init__.py
sch/cli.py
sch/commands.py
sch/errors.py
sch/readme.py
sch/server.py
sch/utils.py
scholar_search-0.0.6.dist-info/LICENSE
scholar_search-0.0.6.dist-info/METADATA
scholar_search-0.0.6.dist-info/WHEEL
scholar_search-0.0.6.dist-info/entry_points.txt
scholar_search-0.0.6.dist-info/top_level.txt
scholar_search-0.0.6.dist-info/RECORD
